MANIFEST.in
README.txt
setup.py
collective/__init__.py
collective.properties.egg-info/PKG-INFO
collective.properties.egg-info/SOURCES.txt
collective.properties.egg-info/dependency_links.txt
collective.properties.egg-info/entry_points.txt
collective.properties.egg-info/namespace_packages.txt
collective.properties.egg-info/not-zip-safe
collective.properties.egg-info/requires.txt
collective.properties.egg-info/top_level.txt
collective/properties/TODO.txt
collective/properties/__init__.py
collective/properties/browser.py
collective/properties/config.py
collective/properties/configure.zcml
collective/properties/converter.py
collective/properties/field.py
collective/properties/interfaces.py
collective/properties/propertytypes.py
collective/properties/vocabulary.py
collective/properties/widget.py
collective/properties/profiles/default/actions.xml
collective/properties/profiles/default/metadata.xml
collective/properties/templates/orderedselect_input.pt
docs/HISTORY.txt
docs/INSTALL.txt
docs/LICENSE.GPL
docs/LICENSE.txt