Metadata-Version: 1.0
Name: collective.properties
Version: 1.0a2
Summary: Provides form to update object properties via Plone UI.
Home-page: http://svn.plone.org/svn/collective/collective.properties
Author: Vitaliy Podoba
Author-email: vitaliypodoba@gmail.com
License: GPL
Keywords: plone properties form ui
Platform: UNKNOWN
Classifier: Programming Language :: Python
